ruspython.py
ruspython_translator-0.1.1.dist-info/LICENSE.md
ruspython_translator-0.1.1.dist-info/METADATA
ruspython_translator-0.1.1.dist-info/WHEEL
ruspython_translator-0.1.1.dist-info/top_level.txt
ruspython_translator-0.1.1.dist-info/RECORD
