Metadata-Version: 2.1
Name: ruspython-translator
Version: 0.1.1
Summary: Библиотека для выполнения Python кода с русскими ключевыми словами
Home-page: https://github.com/BOTSISQ/RuPy
Author: Robot
Author-email: flep2019@mail.ru
Keywords: russian python,python на русском,транслятор,интерпретатор
Classifier: Programming Language :: Python :: 3
Classifier: License :: OSI Approved :: MIT License
Classifier: Operating System :: OS Independent
Classifier: Topic :: Software Development :: Interpreters
Classifier: Topic :: Software Development :: Libraries :: Python Modules
Classifier: Natural Language :: Russian
Requires-Python: >=3.6
License-File: LICENSE.md
